aiohttp_oauth_client/__init__.py
aiohttp_oauth_client/assertion_client.py
aiohttp_oauth_client/base.py
aiohttp_oauth_client/oauth1_client.py
aiohttp_oauth_client/oauth2_client.py
aiohttp_oauth_client-0.1.1.dist-info/LICENSE
aiohttp_oauth_client-0.1.1.dist-info/METADATA
aiohttp_oauth_client-0.1.1.dist-info/WHEEL
aiohttp_oauth_client-0.1.1.dist-info/top_level.txt
aiohttp_oauth_client-0.1.1.dist-info/RECORD
